{
  "16": {
    "name": "Firming Hydrating Oil Serum",
    "image": "https://oss-cf.cjdropshipping.com/product/2026/04/09/11/201b621e-c2a7-4467-8c2e-1300559489dc.jpg",
    "images": [],
    "price": 1.74,
    "pid": "2604090451561615200"
  },
  "17": {
    "name": "Exfoliating Kojic Acid Arbutin Turmeric Serum 80ml",
    "image": "https://cf.cjdropshipping.com/7347eb25-5374-4bc2-97f5-c919004348f4.jpg",
    "images": [],
    "price": 2.99,
    "pid": "2042437432425881601"
  },
  "18": {
    "name": "Firming Hydrating Oil Serum",
    "image": "https://oss-cf.cjdropshipping.com/product/2026/04/09/11/201b621e-c2a7-4467-8c2e-1300559489dc.jpg",
    "images": [],
    "price": 1.74,
    "pid": "2604090451561615200"
  },
  "19": {
    "name": "Firming Hydrating Oil Serum",
    "image": "https://oss-cf.cjdropshipping.com/product/2026/04/09/11/201b621e-c2a7-4467-8c2e-1300559489dc.jpg",
    "images": [],
    "price": 1.74,
    "pid": "2604090451561615200"
  },
  "20": {
    "name": "Nail Care Pen Set",
    "image": "https://oss-cf.cjdropshipping.com/product/2026/04/10/04/112e4c33-f9ef-4727-9eda-e49c21fc1e5e.jpg",
    "images": [],
    "price": 2.81,
    "pid": "2604100433501612900"
  },
  "21": {
    "name": "Premium Bamboo Fiber Exfoliating Body Scrubber Towel Deep Clean & Gentle Exfoliation For Smooth Skin-Beige",
    "image": "https://cf.cjdropshipping.com/62836d6c-9832-4e3b-b45d-9582cfe717f4.png",
    "images": [],
    "price": 11.43,
    "pid": "2042439359557574657"
  },
  "22": {
    "name": "Premium Bamboo Fiber Exfoliating Body Scrubber Towel Deep Clean & Gentle Exfoliation For Smooth Skin-Beige",
    "image": "https://cf.cjdropshipping.com/62836d6c-9832-4e3b-b45d-9582cfe717f4.png",
    "images": [],
    "price": 11.43,
    "pid": "2042439359557574657"
  },
  "23": {
    "name": "Brightening And Moisturizing Cream",
    "image": "https://oss-cf.cjdropshipping.com/product/2026/04/10/03/6c8f8d7a-f7fb-46b3-a20b-3a25e84aeb02.jpg",
    "images": [],
    "price": 1.74,
    "pid": "2604100400091626200"
  },
  "24": {
    "name": "Electric Foot Grinder, Automatic Foot Rubbing, Calluses Removal, And Foot Repair ToolWhite",
    "image": "https://cf.cjdropshipping.com/91443d17-6837-4b6a-9044-191286a2d955.jpg",
    "images": [],
    "price": 17.02,
    "pid": "2042142143157465090"
  },
  "25": {
    "name": "Firming Hydrating Oil Serum",
    "image": "https://oss-cf.cjdropshipping.com/product/2026/04/09/11/201b621e-c2a7-4467-8c2e-1300559489dc.jpg",
    "images": [],
    "price": 1.74,
    "pid": "2604090451561615200"
  },
  "26": {
    "name": "Silicone Pad For 40-Ounce Cup Beverage Separator",
    "image": "https://oss-cf.cjdropshipping.com/product/2026/04/07/07/8d1ad809-0b06-4c83-be9f-4c3f0f8310e6.jpg",
    "images": [],
    "price": 3.35,
    "pid": "2604070702191608100"
  },
  "27": {
    "name": "Ginseng Brightening Eye Cream",
    "image": "https://oss-cf.cjdropshipping.com/product/2026/04/09/04/0c752e0d-0e46-49b7-8bdf-1ae3d3a6b7a8.jpg",
    "images": [],
    "price": 1.74,
    "pid": "2604090406311626100"
  },
  "28": {
    "name": "Coconut Sunscreen Lip Balm",
    "image": "https://oss-cf.cjdropshipping.com/product/2026/04/09/04/89875778-c85a-499b-8497-39ed80ef0844.jpg",
    "images": [],
    "price": 1.74,
    "pid": "2604090413591601800"
  },
  "29": {
    "name": "Galaxy Starry Sky Projector Night Light Rotating LED Planetarium Star Lamp UK",
    "image": "https://cf.cjdropshipping.com/c4f13610-673d-4d87-b5cd-86fdd2b62989.jpg",
    "images": [],
    "price": 17.42,
    "pid": "2042478274867527681"
  },
  "30": {
    "name": "Nail Care Pen Set",
    "image": "https://oss-cf.cjdropshipping.com/product/2026/04/10/04/112e4c33-f9ef-4727-9eda-e49c21fc1e5e.jpg",
    "images": [],
    "price": 2.81,
    "pid": "2604100433501612900"
  },
  "31": {
    "name": "French-style White-edged Ready-made Nail Tips With Red Little Hearts",
    "image": "https://cf.cjdropshipping.com/quick/product/981c76d5-73c9-4d9b-9247-b82fb80ed709.jpg",
    "images": [],
    "price": 0.64,
    "pid": "2604100159061633400"
  },
  "32": {
    "name": "Small-leaf Acacia Wood Cooking Set Kitchen Tools Wood",
    "image": "https://cf.cjdropshipping.com/quick/product/c668b7a5-3dbf-44db-be05-f2fefdee296c.jpg",
    "images": [],
    "price": 3.41,
    "pid": "2604100509301622700"
  },
  "33": {
    "name": "Nail Care Pen Set",
    "image": "https://oss-cf.cjdropshipping.com/product/2026/04/10/04/112e4c33-f9ef-4727-9eda-e49c21fc1e5e.jpg",
    "images": [],
    "price": 2.81,
    "pid": "2604100433501612900"
  },
  "34": {
    "name": "Perfumed Hair Oil To Repair Dry, Damaged Hair And Reduce Frizz",
    "image": "https://oss-cf.cjdropshipping.com/product/2026/04/09/05/51c20d20-3b52-405b-9299-34d808738c7b_fine.jpeg",
    "images": [],
    "price": 0.63,
    "pid": "2604090557291603300"
  },
  "35": {
    "name": "Perfumed Hair Oil To Repair Dry, Damaged Hair And Reduce Frizz",
    "image": "https://oss-cf.cjdropshipping.com/product/2026/04/09/05/51c20d20-3b52-405b-9299-34d808738c7b_fine.jpeg",
    "images": [],
    "price": 0.63,
    "pid": "2604090557291603300"
  },
  "36": {
    "name": "2200W Professional Style Hair Dryer Nozzle Concentrator Blower Pro Salon Heat UK",
    "image": "https://cf.cjdropshipping.com/83806178-f468-4753-8eb9-6900249e1858.jpg",
    "images": [],
    "price": 13.39,
    "pid": "2042494666157629441"
  },
  "37": {
    "name": "Copper-gold Leopard-print Plain Satin Faux-silk Midi Skirt",
    "image": "https://cf.cjdropshipping.com/quick/product/5dc34dfa-af2d-4be1-98ad-982f9a82746a.jpg",
    "images": [],
    "price": 9.93,
    "pid": "2604090611141603400"
  },
  "38": {
    "name": "Copper-gold Leopard-print Plain Satin Faux-silk Midi Skirt",
    "image": "https://cf.cjdropshipping.com/quick/product/5dc34dfa-af2d-4be1-98ad-982f9a82746a.jpg",
    "images": [],
    "price": 9.93,
    "pid": "2604090611141603400"
  },
  "39": {
    "name": "Spare Tire Wall Mount Carrier Holder Wear Resistant Save Space Wheel Bracket Kit",
    "image": "https://cf.cjdropshipping.com/e92c59f0-3daf-44b4-8722-0df72ff43672.jpg",
    "images": [],
    "price": 9.17,
    "pid": "2042489259309703169"
  },
  "40": {
    "name": "Black Large Microfiber Car Cleaning Soft Cloth Car Wash, Kitchen Cleaning Towel",
    "image": "https://cf.cjdropshipping.com/4490a867-2a1e-4b6b-a293-8be48ad4bea0.jpg",
    "images": [],
    "price": 11.56,
    "pid": "2042508659718922242"
  },
  "41": null,
  "42": {
    "name": "EELHOE Foot Soak Bath Bombs With Old Ginger For Foot Skin Care",
    "image": "https://cf.cjdropshipping.com/quick/product/df9816a7-4650-4b08-9549-153a5e4fa44e.jpg",
    "images": [],
    "price": 1.55,
    "pid": "2604090837381615800"
  },
  "43": {
    "name": "Moisturizing Foot Mask",
    "image": "https://oss-cf.cjdropshipping.com/product/2026/04/09/04/9bcafefa-286f-49f1-a750-f1bb07e0d41e.jpg",
    "images": [],
    "price": 2.28,
    "pid": "2604090436211627100"
  },
  "44": {
    "name": "Hoygi Hydrocolloid Nose Patch, Hydrocolloid Invisible Concealer To Remove Blackheads And Acne Facial Pore Cleaning Nose Patch",
    "image": "https://cf.cjdropshipping.com/cbae6b94-7a7a-4cd1-9865-fc7dd7f35ff8.jpg",
    "images": [],
    "price": 8.22,
    "pid": "2034262753225895937"
  },
  "45": {
    "name": "Powerful Car Vacuum Cleaner Wet Dry Cordless Strong Suction Handheld Cleaning UK",
    "image": "https://cf.cjdropshipping.com/e68a6b72-9393-436d-95d6-d1b8a3ea71de.jpg",
    "images": [],
    "price": 12.47,
    "pid": "2041456530893991938"
  },
  "46": {
    "name": "Washable And Reusable Beauty Sponge, Highly Elastic And Soft Makeup Sponge, Portable Travel Makeup Puff, Suitable For Women And Girls.",
    "image": "https://cf.cjdropshipping.com/75c012e7-5616-465f-a161-0835b89544c2.png",
    "images": [],
    "price": 9.83,
    "pid": "2042084382950342658"
  },
  "47": {
    "name": "Washable And Reusable Beauty Sponge, Highly Elastic And Soft Makeup Sponge, Portable Travel Makeup Puff, Suitable For Women And Girls.",
    "image": "https://cf.cjdropshipping.com/75c012e7-5616-465f-a161-0835b89544c2.png",
    "images": [],
    "price": 9.83,
    "pid": "2042084382950342658"
  },
  "48": {
    "name": "APP Control 5-In-1 RGB LED Interior Strip Light Car Ambient Atmosphere Lighting",
    "image": "https://cf.cjdropshipping.com/98cd3084-c017-4355-95e8-014dac171184.jpg",
    "images": [],
    "price": 14.39,
    "pid": "2042511065751920641"
  },
  "49": {
    "name": "Traceless Makeup Brush Set",
    "image": "https://oss-cf.cjdropshipping.com/product/2026/04/09/04/defee522-56ef-4eb0-8dbd-c1883bd8fbfe.jpg",
    "images": [],
    "price": 2.28,
    "pid": "2604090419211637100"
  },
  "50": {
    "name": "Professional Hair Dryer Fast Drying Ionic Hairdryer With Diffuser Hairdrye UK",
    "image": "https://cf.cjdropshipping.com/426d7de4-f423-4994-a348-11c18babda9a.jpg",
    "images": [],
    "price": 13.49,
    "pid": "2042478828641886209"
  }
}